{
  "plays": {
    "werewolf": 38,
    "billiard": 41,
    "thirteen": 77,
    "baucua": 75,
    "youtube": 46,
    "dotsandboxes": 25,
    "draw": 31,
    "maze": 46,
    "gunnywars": 127,
    "monopoly": 44,
    "tictactoe": 10,
    "caro": 117,
    "poker": 40,
    "oanquan": 25,
    "uno": 22,
    "chess": 15,
    "connect4": 13,
    "ludo": 22,
    "reversi": 13,
    "explodingkittens": 59,
    "irokaruta": 15,
    "phom": 9
  },
  "dataTransfer": {
    "billiard": 750105,
    "baucua": 337102,
    "monopoly": 3473517,
    "gunnywars": 630225,
    "caro": 1794658,
    "maze": 332046,
    "poker": 617575,
    "oanquan": 56599,
    "uno": 618671,
    "draw": 6162181,
    "thirteen": 2051551,
    "werewolf": 144003,
    "connect4": 153167,
    "dotsandboxes": 200185,
    "chess": 9387,
    "ludo": 930345,
    "reversi": 244542,
    "tictactoe": 12857,
    "youtube": 12426,
    "explodingkittens": 695866,
    "irokaruta": 11801,
    "phom": 90172
  }
}